<?xml version="1.0" encoding="utf-8"?>
<!--
	(c) lvcharts.net
	Map Version 1.0

	This work is licensed under a Creative Commons
	Attribution-NonCommercial-ShareAlike 4.0 International License
	https://creativecommons.org/licenses/by-nc-sa/4.0/
-->
<LiveChartsMap xmlns:xsi="http://www.w3.org/2001/XMLSchema-instance" xmlns:xsd="http://www.w3.org/2001/XMLSchema">
  <Height>2087</Height>
  <Width>3739</Width>
  <Shapes>
    <MapShape>
      <Id>1909</Id>
      <Name>Chhukha</Name>
      <Path>M934,1389L942,1387L977,1397L983,1400L985,1411L922,1455L899,1485L900,1495L929,1511L942,1521L969,1535L995,1531L1011,1556L1032,1619L1059,1627L1065,1640L1063,1647L1061,1653L1058,1670L1128,1670L1150,1714L1156,1730L1170,1786L1151,1825L1150,1841L1152,1846L1165,1864L1170,1880L1171,1893L1170,1909L1167,1924L1165,1933L1157,1948L1155,1952L1149,1957L1141,1976L1131,1982L1120,2013L1124,2039L1133,2051L1139,2059L1141,2063L1141,2076L1141,2081L1141,2081L1123,2078L1063,2052L1039,2050L1000,2067L979,2067L966,2056L983,2022L981,2000L953,1977L909,1961L863,1953L794,1961L754,1941L711,1911L711,1911L711,1884L707,1864L701,1863L692,1863L669,1868L664,1867L663,1864L665,1859L665,1854L661,1846L656,1827L648,1821L625,1808L618,1806L614,1807L611,1809L605,1808L602,1806L598,1795L636,1768L680,1708L684,1681L681,1675L677,1666L671,1660L665,1654L659,1652L646,1649L646,1617L642,1593L646,1578L651,1569L667,1559L668,1536L681,1514L691,1500L692,1491L690,1485L682,1477L677,1470L668,1444L746,1446L777,1452L791,1458L810,1469L820,1471L854,1476L864,1472L865,1468L866,1464L865,1460L863,1456L862,1451L861,1442L862,1431L878,1383L885,1367L889,1355L892,1324L911,1338L918,1352L922,1365L926,1383L930,1388L934,1389Z</Path>
    </MapShape>
    <MapShape>
      <Id>1910</Id>
      <Name>Daga</Name>
      <Path>M1179,1381L1212,1378L1221,1382L1237,1393L1251,1406L1275,1426L1286,1439L1294,1451L1297,1457L1303,1472L1317,1498L1343,1533L1389,1539L1432,1558L1450,1561L1479,1579L1484,1620L1478,1641L1486,1652L1485,1680L1480,1719L1480,1724L1480,1760L1469,1793L1452,1813L1442,1832L1422,1843L1418,1852L1419,1858L1417,1869L1417,1874L1419,1885L1419,1889L1378,1916L1374,1921L1369,1928L1372,1930L1375,1931L1377,1932L1376,1936L1371,1937L1365,1936L1360,1932L1357,1927L1356,1918L1354,1909L1350,1900L1341,1893L1336,1892L1333,1895L1334,1907L1332,1916L1329,1926L1325,1936L1321,1940L1317,1941L1314,1939L1312,1936L1311,1932L1310,1929L1308,1923L1302,1938L1296,1942L1267,1953L1257,1953L1249,1950L1238,1938L1230,1931L1216,1925L1209,1925L1206,1928L1207,1938L1206,1943L1205,1948L1203,1951L1201,1959L1186,1952L1182,1951L1174,1951L1169,1952L1149,1957L1155,1952L1157,1948L1165,1933L1167,1924L1170,1909L1171,1893L1170,1880L1165,1864L1152,1846L1150,1841L1151,1825L1170,1786L1156,1730L1150,1714L1128,1670L1058,1670L1061,1653L1063,1647L1065,1640L1059,1627L1032,1619L1011,1556L995,1531L1006,1498L1010,1469L1015,1453L1021,1444L1026,1440L1032,1436L1045,1431L1052,1428L1061,1418L1069,1405L1078,1379L1090,1382L1155,1368L1179,1381Z</Path>
    </MapShape>
    <MapShape>
      <Id>1911</Id>
      <Name>Ha</Name>
      <Path>M414,927L417,930L439,954L474,983L488,989L493,990L499,993L513,1003L516,1005L520,1005L525,1004L530,1002L536,1003L541,1011L561,1073L565,1088L575,1109L588,1120L596,1129L603,1134L607,1154L620,1172L650,1224L667,1248L713,1315L704,1329L690,1341L683,1344L667,1351L660,1355L653,1362L649,1371L647,1381L656,1403L658,1416L668,1444L677,1470L682,1477L690,1485L692,1491L691,1500L681,1514L668,1536L667,1559L616,1549L592,1560L582,1582L579,1592L564,1615L563,1616L513,1550L475,1584L459,1583L455,1578L453,1567L451,1562L448,1558L446,1554L443,1551L441,1547L440,1543L439,1536L434,1527L354,1519L333,1509L331,1505L331,1501L330,1496L327,1491L322,1482L320,1476L318,1471L317,1467L317,1464L317,1461L317,1459L316,1455L314,1450L312,1445L312,1439L307,1427L304,1425L300,1425L293,1430L290,1433L284,1438L272,1439L245,1409L231,1382L225,1378L217,1373L178,1363L163,1357L172,1350L181,1313L206,1294L246,1297L269,1317L297,1294L280,1264L260,1216L246,1166L253,1136L263,1109L282,1091L278,1084L273,1073L270,1060L276,1044L292,1035L306,1019L304,1006L319,987L338,983L345,963L357,946L372,936L402,924L414,927Z</Path>
    </MapShape>
    <MapShape>
      <Id>1912</Id>
      <Name>Paro</Name>
      <Path>M717,898L734,895L742,898L752,904L772,923L797,957L813,989L825,1000L837,1006L828,1026L826,1041L825,1071L816,1127L815,1174L823,1187L832,1192L837,1193L851,1198L855,1203L858,1213L859,1226L851,1260L880,1277L887,1285L891,1291L892,1320L892,1324L889,1355L885,1367L878,1383L862,1431L861,1442L862,1451L863,1456L865,1460L866,1464L865,1468L864,1472L854,1476L820,1471L810,1469L791,1458L777,1452L746,1446L668,1444L658,1416L656,1403L647,1381L649,1371L653,1362L660,1355L667,1351L683,1344L690,1341L704,1329L713,1315L667,1248L650,1224L620,1172L607,1154L603,1134L596,1129L588,1120L575,1109L565,1088L561,1073L541,1011L536,1003L530,1002L525,1004L520,1005L516,1005L513,1003L499,993L493,990L488,989L474,983L439,954L417,930L414,927L418,927L422,928L434,933L439,938L442,922L474,874L521,792L530,771L549,777L555,780L572,785L577,787L584,795L588,797L611,805L619,807L629,805L641,797L653,790L680,789L692,787L708,777L729,770L727,807L727,815L729,831L731,838L748,863L717,898Z</Path>
    </MapShape>
    <MapShape>
      <Id>1913</Id>
      <Name>Gasa</Name>
      <Path>M1780,130L1808,75L1844,75L1877,96L1921,96L1976,138L2024,142L2068,158L2079,200L2046,212L2024,254L1987,258L1954,296L1943,362L1892,362L1868,381L1866,407L1858,423L1847,442L1836,451L1801,472L1794,484L1792,495L1795,502L1794,511L1795,517L1797,523L1800,529L1801,535L1801,547L1802,555L1803,562L1800,569L1794,574L1782,574L1775,576L1768,576L1753,572L1745,572L1739,575L1733,581L1727,584L1720,585L1711,579L1696,565L1674,529L1672,521L1672,518L1672,515L1674,511L1672,506L1668,498L1650,482L1632,483L1595,486L1590,487L1585,491L1580,498L1572,519L1525,601L1521,610L1513,620L1504,630L1481,642L1469,647L1446,651L1440,652L1435,653L1430,654L1426,658L1422,663L1416,703L1398,699L1393,696L1380,686L1328,665L1302,642L1295,638L1289,637L1282,639L1268,646L1260,648L1253,650L1247,650L1232,653L1227,655L1220,662L1214,671L1192,708L1156,755L1124,758L1106,761L1085,775L1090,787L1046,801L1026,794L1017,792L1010,792L997,793L990,795L985,797L978,811L936,787L932,783L927,778L925,768L917,748L914,733L890,731L882,735L880,739L873,749L865,761L861,763L857,762L853,761L850,758L847,756L844,753L842,750L839,746L838,743L835,735L844,724L850,697L851,687L851,679L849,672L847,662L849,655L855,646L893,595L899,590L905,586L910,583L918,577L919,573L916,571L888,565L874,560L867,548L860,506L847,487L816,470L807,466L791,465L765,467L769,460L769,460L795,414L811,393L830,376L852,367L874,350L926,283L945,270L966,264L1100,240L1142,220L1162,184L1170,164L1187,150L1224,126L1234,115L1251,90L1261,79L1273,73L1282,77L1320,54L1361,64L1382,51L1403,48L1493,17L1551,29L1584,46L1610,42L1635,13L1665,0L1705,29L1705,75L1738,123L1780,130Z</Path>
    </MapShape>
    <MapShape>
      <Id>1914</Id>
      <Name>Samchi</Name>
      <Path>M272,1439L284,1438L290,1433L293,1430L300,1425L304,1425L307,1427L312,1439L312,1445L314,1450L316,1455L317,1459L317,1461L317,1464L317,1467L318,1471L320,1476L322,1482L327,1491L330,1496L331,1501L331,1505L333,1509L354,1519L434,1527L439,1536L440,1543L441,1547L443,1551L446,1554L448,1558L451,1562L453,1567L455,1578L459,1583L475,1584L513,1550L563,1616L564,1615L579,1592L582,1582L592,1560L616,1549L667,1559L651,1569L646,1578L642,1593L646,1617L646,1649L659,1652L665,1654L671,1660L677,1666L681,1675L684,1681L680,1708L636,1768L598,1795L602,1806L605,1808L611,1809L614,1807L618,1806L625,1808L648,1821L656,1827L661,1846L665,1854L665,1859L663,1864L664,1867L669,1868L692,1863L701,1863L707,1864L711,1884L711,1911L711,1911L681,1890L635,1902L619,1901L605,1903L593,1912L582,1924L569,1933L537,1941L506,1944L443,1941L408,1931L392,1913L383,1887L368,1856L350,1836L324,1817L297,1804L273,1806L262,1813L250,1817L237,1816L225,1809L217,1796L217,1784L219,1771L216,1756L197,1732L174,1734L153,1753L135,1776L129,1714L129,1714L129,1646L123,1614L109,1586L84,1567L14,1529L3,1522L0,1519L9,1483L27,1442L51,1407L79,1387L146,1370L163,1357L178,1363L217,1373L225,1378L231,1382L245,1409L272,1439Z</Path>
    </MapShape>
    <MapShape>
      <Id>1915</Id>
      <Name>Thimphu</Name>
      <Path>M861,763L865,761L873,749L880,739L882,735L890,731L914,733L917,748L925,768L927,778L932,783L936,787L978,811L995,837L997,842L1002,873L1003,898L1000,913L999,921L1002,931L1008,943L1017,954L1024,966L1033,986L1039,998L1054,1012L1068,1033L1098,1009L1143,994L1151,1006L1169,1034L1171,1040L1177,1048L1181,1050L1207,1054L1209,1065L1209,1072L1207,1085L1203,1100L1185,1116L1127,1133L1122,1156L1120,1180L1129,1205L1069,1257L1078,1267L1087,1274L1090,1276L1092,1279L1093,1292L1090,1305L1090,1382L1078,1379L1069,1405L1061,1418L1052,1428L1045,1431L1032,1436L1026,1440L1021,1444L1015,1453L1010,1469L1006,1498L995,1531L969,1535L942,1521L929,1511L900,1495L899,1485L922,1455L985,1411L983,1400L977,1397L942,1387L934,1389L930,1388L926,1383L922,1365L918,1352L911,1338L892,1324L892,1320L891,1291L887,1285L880,1277L851,1260L859,1226L858,1213L855,1203L851,1198L837,1193L832,1192L823,1187L815,1174L816,1127L825,1071L826,1041L828,1026L837,1006L825,1000L813,989L797,957L772,923L752,904L742,898L734,895L717,898L748,863L731,838L729,831L727,815L727,807L729,770L708,777L692,787L680,789L653,790L641,797L629,805L619,807L611,805L588,797L584,795L577,787L572,785L555,780L549,777L530,771L542,741L551,695L588,670L634,649L675,618L713,567L765,467L791,465L807,466L816,470L847,487L860,506L867,548L874,560L888,565L916,571L919,573L918,577L910,583L905,586L899,590L893,595L855,646L849,655L847,662L849,672L851,679L851,687L850,697L844,724L835,735L838,743L839,746L842,750L844,753L847,756L850,758L853,761L857,762L861,763Z</Path>
    </MapShape>
    <MapShape>
      <Id>1916</Id>
      <Name>Punakha</Name>
      <Path>M1416,703L1418,741L1407,762L1396,772L1379,791L1374,797L1372,804L1369,813L1368,827L1369,840L1378,849L1386,853L1394,854L1408,852L1416,852L1424,856L1432,863L1441,874L1450,883L1454,889L1454,899L1451,906L1435,923L1410,931L1382,969L1343,1002L1343,1002L1337,1021L1311,1043L1256,1057L1255,1057L1209,1054L1207,1054L1181,1050L1177,1048L1171,1040L1169,1034L1151,1006L1143,994L1098,1009L1068,1033L1054,1012L1039,998L1033,986L1024,966L1017,954L1008,943L1002,931L999,921L1000,913L1003,898L1002,873L997,842L995,837L978,811L985,797L990,795L997,793L1010,792L1017,792L1026,794L1046,801L1090,787L1085,775L1106,761L1124,758L1156,755L1192,708L1214,671L1220,662L1227,655L1232,653L1247,650L1253,650L1260,648L1268,646L1282,639L1289,637L1295,638L1302,642L1328,665L1380,686L1393,696L1398,699L1416,703Z</Path>
    </MapShape>
    <MapShape>
      <Id>1897</Id>
      <Name>Bumthang</Name>
      <Path>M2254,383L2249,423L2249,436L2250,446L2254,459L2255,488L2253,498L2250,503L2239,510L2234,516L2231,522L2229,531L2224,542L2225,548L2229,554L2242,566L2250,570L2257,573L2269,575L2275,578L2281,585L2298,624L2301,657L2316,664L2333,681L2341,693L2348,700L2352,703L2360,705L2365,707L2376,714L2383,717L2386,725L2397,774L2397,804L2400,808L2407,812L2425,814L2430,815L2435,818L2466,849L2470,858L2473,870L2478,899L2480,928L2472,955L2462,987L2460,996L2460,1000L2470,1023L2472,1053L2471,1060L2469,1067L2468,1072L2470,1079L2476,1087L2488,1096L2506,1119L2488,1158L2483,1165L2478,1171L2476,1179L2476,1185L2493,1220L2471,1227L2467,1229L2451,1246L2447,1259L2444,1262L2437,1266L2429,1270L2403,1271L2389,1282L2376,1284L2341,1300L2306,1283L2293,1269L2290,1263L2288,1259L2278,1251L2269,1241L2264,1237L2257,1235L2252,1235L2246,1235L2239,1236L2231,1240L2225,1244L2220,1271L2159,1204L2136,1188L2128,1183L2113,1179L2103,1174L2097,1170L2092,1162L2089,1159L2084,1157L2073,1155L2046,1145L2037,1119L2043,1104L2038,1072L2012,982L2003,977L1999,961L1994,927L1991,923L1986,919L1985,913L1985,904L1987,889L1987,879L1988,872L1996,844L1999,811L1999,797L1998,786L1995,780L1993,775L1980,756L1977,752L1971,749L1965,747L1959,746L1954,747L1950,748L1947,748L1944,745L1940,742L1931,735L1923,685L1924,679L1927,673L1931,674L1936,670L1943,660L1956,636L1962,600L1961,588L1959,580L1957,575L1954,571L1951,566L1949,557L1947,551L1944,546L1941,544L1937,542L1924,539L1921,537L1919,532L1915,524L1912,515L1909,509L1906,504L1905,501L1905,499L1907,496L1909,493L1912,488L1915,482L1919,471L1918,462L1916,453L1891,421L1909,391L1943,362L1962,359L1981,359L2054,370L2079,364L2106,361L2138,343L2157,339L2175,343L2223,375L2254,383Z</Path>
    </MapShape>
    <MapShape>
      <Id>1898</Id>
      <Name>Chirang</Name>
      <Path>M1572,1515L1612,1512L1628,1506L1634,1506L1638,1508L1654,1522L1666,1529L1676,1539L1709,1521L1733,1513L1762,1495L1783,1522L1767,1533L1754,1540L1736,1552L1727,1560L1711,1576L1708,1584L1706,1609L1703,1621L1692,1652L1675,1669L1677,1712L1660,1741L1641,1760L1632,1777L1631,1790L1623,1804L1606,1815L1566,1876L1565,1880L1565,1884L1566,1887L1567,1890L1567,1893L1568,1902L1564,1907L1556,1910L1536,1914L1525,1918L1511,1928L1506,1936L1499,1942L1490,1946L1465,1941L1450,1938L1443,1933L1431,1915L1429,1901L1419,1889L1419,1885L1417,1874L1417,1869L1419,1858L1418,1852L1422,1843L1442,1832L1452,1813L1469,1793L1480,1760L1480,1724L1480,1719L1485,1680L1486,1652L1478,1641L1484,1620L1479,1579L1477,1493L1500,1487L1557,1512L1572,1515Z</Path>
    </MapShape>
    <MapShape>
      <Id>1899</Id>
      <Name>Geylegphug</Name>
      <Path>M1939,1543L1943,1542L1950,1542L1956,1543L1973,1549L1989,1551L1996,1571L2016,1591L2034,1605L2063,1621L2079,1628L2085,1629L2091,1629L2097,1627L2106,1622L2115,1618L2141,1632L2151,1644L2157,1652L2158,1665L2160,1676L2167,1684L2170,1691L2170,1704L2171,1711L2174,1721L2175,1727L2173,1737L2166,1747L2171,1767L2181,1772L2215,1777L2220,1781L2228,1788L2237,1802L2244,1811L2249,1813L2256,1815L2260,1818L2266,1825L2277,1832L2285,1847L2287,1855L2299,1877L2301,1884L2306,1910L2313,1926L2319,1933L2325,1936L2344,1932L2385,1936L2396,1938L2401,1939L2442,1936L2446,1935L2450,1932L2469,1923L2480,1973L2477,1975L2474,1977L2467,1979L2465,1984L2465,1984L2212,1999L2068,1982L1943,1917L1840,1843L1802,1837L1779,1844L1763,1857L1749,1872L1730,1886L1710,1893L1669,1892L1648,1893L1611,1918L1583,1993L1555,2018L1513,2030L1386,2043L1316,2061L1292,2064L1280,2062L1258,2055L1256,2055L1248,2053L1243,2051L1235,2043L1230,2043L1224,2048L1222,2054L1221,2060L1221,2063L1221,2065L1219,2073L1216,2081L1210,2087L1206,2087L1196,2083L1191,2082L1147,2082L1141,2081L1141,2081L1141,2076L1141,2063L1139,2059L1133,2051L1124,2039L1120,2013L1131,1982L1141,1976L1149,1957L1169,1952L1174,1951L1182,1951L1186,1952L1201,1959L1203,1951L1205,1948L1206,1943L1207,1938L1206,1928L1209,1925L1216,1925L1230,1931L1238,1938L1249,1950L1257,1953L1267,1953L1296,1942L1302,1938L1308,1923L1310,1929L1311,1932L1312,1936L1314,1939L1317,1941L1321,1940L1325,1936L1329,1926L1332,1916L1334,1907L1333,1895L1336,1892L1341,1893L1350,1900L1354,1909L1356,1918L1357,1927L1360,1932L1365,1936L1371,1937L1376,1936L1377,1932L1375,1931L1372,1930L1369,1928L1374,1921L1378,1916L1419,1889L1429,1901L1431,1915L1443,1933L1450,1938L1465,1941L1490,1946L1499,1942L1506,1936L1511,1928L1525,1918L1536,1914L1556,1910L1564,1907L1568,1902L1567,1893L1567,1890L1566,1887L1565,1884L1565,1880L1566,1876L1606,1815L1623,1804L1631,1790L1632,1777L1641,1760L1660,1741L1677,1712L1675,1669L1692,1652L1703,1621L1706,1609L1708,1584L1711,1576L1727,1560L1736,1552L1754,1540L1767,1533L1783,1522L1762,1495L1762,1475L1773,1462L1788,1446L1859,1486L1895,1515L1909,1524L1917,1534L1924,1538L1929,1541L1934,1542L1939,1543Z</Path>
    </MapShape>
    <MapShape>
      <Id>1900</Id>
      <Name>Lhuntshi</Name>
      <Path>M3013,466L2993,488L2977,503L2971,506L2965,506L2954,503L2949,503L2943,507L2907,550L2902,554L2897,555L2891,556L2887,558L2883,564L2882,571L2883,586L2879,690L2874,712L2875,725L2872,746L2867,761L2862,770L2860,779L2861,788L2869,817L2869,826L2864,857L2869,933L2858,960L2872,980L2860,983L2856,984L2850,987L2847,993L2848,1013L2846,1023L2820,1046L2808,1058L2800,1079L2806,1095L2814,1105L2816,1111L2814,1134L2800,1171L2710,1220L2684,1179L2677,1174L2655,1170L2636,1169L2612,1177L2550,1232L2493,1220L2476,1185L2476,1179L2478,1171L2483,1165L2488,1158L2506,1119L2488,1096L2476,1087L2470,1079L2468,1072L2469,1067L2471,1060L2472,1053L2470,1023L2460,1000L2460,996L2462,987L2472,955L2480,928L2478,899L2473,870L2470,858L2466,849L2435,818L2430,815L2425,814L2407,812L2400,808L2397,804L2397,774L2386,725L2383,717L2376,714L2365,707L2360,705L2352,703L2348,700L2341,693L2333,681L2316,664L2301,657L2298,624L2281,585L2275,578L2269,575L2257,573L2250,570L2242,566L2229,554L2225,548L2224,542L2229,531L2231,522L2234,516L2239,510L2250,503L2253,498L2255,488L2254,459L2250,446L2249,436L2249,423L2254,383L2292,393L2361,397L2426,412L2483,460L2499,475L2537,495L2585,500L2630,489L2660,460L2660,459L2660,459L2676,435L2723,380L2744,364L2772,358L2801,363L2827,361L2850,338L2872,382L2907,414L2993,460L3013,466Z</Path>
    </MapShape>
    <MapShape>
      <Id>1901</Id>
      <Name>Tashi Yangtse</Name>
      <Path>M3231,756L3224,810L3172,883L3165,931L3189,1024L3200,1041L3231,1067L3241,1088L3259,1108L3284,1116L3312,1121L3336,1132L3336,1132L3336,1134L3333,1141L3327,1149L3318,1153L3288,1158L3249,1174L3184,1195L3172,1196L3146,1226L3141,1230L3114,1241L3110,1246L3007,1210L2964,1205L2982,1170L2984,1159L2983,1154L2969,1120L2892,1016L2872,980L2858,960L2869,933L2864,857L2869,826L2869,817L2861,788L2860,779L2862,770L2867,761L2872,746L2875,725L2874,712L2879,690L2883,586L2882,571L2883,564L2887,558L2891,556L2897,555L2902,554L2907,550L2943,507L2949,503L2954,503L2965,506L2971,506L2977,503L2993,488L3013,466L3024,470L3040,473L3081,473L3125,492L3171,497L3196,504L3219,515L3237,529L3254,558L3249,582L3236,608L3226,638L3225,667L3231,756Z</Path>
    </MapShape>
    <MapShape>
      <Id>1902</Id>
      <Name>Shemgang</Name>
      <Path>M2341,1300L2376,1284L2389,1282L2403,1271L2429,1270L2437,1266L2444,1262L2447,1259L2451,1246L2464,1289L2473,1309L2484,1351L2495,1378L2499,1380L2515,1395L2518,1403L2519,1408L2520,1429L2531,1444L2532,1464L2531,1484L2529,1492L2522,1510L2514,1533L2516,1566L2553,1647L2595,1659L2600,1663L2613,1677L2624,1734L2630,1740L2639,1748L2649,1750L2657,1754L2668,1762L2676,1774L2685,1781L2694,1786L2700,1786L2712,1779L2732,1780L2720,1826L2708,1845L2689,1853L2636,1855L2626,1878L2623,1877L2618,1876L2616,1876L2602,1885L2553,1896L2547,1899L2539,1906L2533,1915L2531,1922L2528,1931L2527,1935L2527,1941L2541,1977L2541,1977L2535,1980L2465,1984L2465,1984L2467,1979L2474,1977L2477,1975L2480,1973L2469,1923L2450,1932L2446,1935L2442,1936L2401,1939L2396,1938L2385,1936L2344,1932L2325,1936L2319,1933L2313,1926L2306,1910L2301,1884L2299,1877L2287,1855L2285,1847L2277,1832L2266,1825L2260,1818L2256,1815L2249,1813L2244,1811L2237,1802L2228,1788L2220,1781L2215,1777L2181,1772L2171,1767L2166,1747L2173,1737L2175,1727L2174,1721L2171,1711L2170,1704L2170,1691L2167,1684L2160,1676L2158,1665L2157,1652L2151,1644L2141,1632L2115,1618L2106,1622L2097,1627L2091,1629L2085,1629L2079,1628L2063,1621L2034,1605L2016,1591L1996,1571L1989,1551L2001,1538L2019,1530L2028,1524L2042,1511L2050,1506L2056,1505L2061,1508L2066,1513L2071,1516L2078,1518L2119,1515L2126,1513L2128,1510L2126,1507L2095,1464L2087,1451L2168,1413L2200,1390L2203,1384L2203,1380L2202,1376L2202,1373L2202,1370L2202,1366L2202,1361L2199,1352L2201,1338L2212,1312L2220,1271L2225,1244L2231,1240L2239,1236L2246,1235L2252,1235L2257,1235L2264,1237L2269,1241L2278,1251L2288,1259L2290,1263L2293,1269L2306,1283L2341,1300Z</Path>
    </MapShape>
    <MapShape>
      <Id>1903</Id>
      <Name>Tongsa</Name>
      <Path>M1950,748L1954,747L1959,746L1965,747L1971,749L1977,752L1980,756L1993,775L1995,780L1998,786L1999,797L1999,811L1996,844L1988,872L1987,879L1987,889L1985,904L1985,913L1986,919L1991,923L1994,927L1999,961L2003,977L2012,982L2038,1072L2043,1104L2037,1119L2046,1145L2073,1155L2084,1157L2089,1159L2092,1162L2097,1170L2103,1174L2113,1179L2128,1183L2136,1188L2159,1204L2220,1271L2212,1312L2201,1338L2199,1352L2202,1361L2202,1366L2202,1370L2202,1373L2202,1376L2203,1380L2203,1384L2200,1390L2168,1413L2087,1451L2095,1464L2126,1507L2128,1510L2126,1513L2119,1515L2078,1518L2071,1516L2066,1513L2061,1508L2056,1505L2050,1506L2042,1511L2028,1524L2019,1530L2001,1538L1989,1551L1973,1549L1956,1543L1950,1542L1943,1542L1939,1543L1934,1542L1929,1541L1924,1538L1917,1534L1909,1524L1895,1515L1859,1486L1788,1446L1809,1416L1815,1395L1815,1379L1796,1367L1791,1332L1786,1320L1778,1310L1745,1280L1740,1273L1738,1267L1739,1263L1739,1258L1740,1254L1726,1236L1708,1204L1702,1166L1699,1156L1679,1122L1719,1112L1726,1107L1745,1088L1755,1083L1770,1079L1778,1078L1785,1080L1790,1083L1794,1082L1797,1080L1801,1076L1806,1072L1818,1060L1785,1044L1773,1029L1754,988L1751,982L1747,971L1746,967L1745,962L1743,957L1738,946L1736,939L1736,931L1751,911L1754,903L1757,880L1759,872L1762,867L1766,861L1770,858L1774,858L1778,859L1782,861L1786,862L1790,862L1796,862L1806,860L1814,857L1820,855L1826,855L1837,863L1842,865L1848,865L1899,843L1910,834L1916,825L1920,811L1931,753L1931,735L1940,742L1944,745L1947,748L1950,748Z</Path>
    </MapShape>
    <MapShape>
      <Id>1904</Id>
      <Name>Wangdi Phodrang</Name>
      <Path>M1931,674L1927,673L1924,679L1923,685L1931,735L1931,753L1920,811L1916,825L1910,834L1899,843L1848,865L1842,865L1837,863L1826,855L1820,855L1814,857L1806,860L1796,862L1790,862L1786,862L1782,861L1778,859L1774,858L1770,858L1766,861L1762,867L1759,872L1757,880L1754,903L1751,911L1736,931L1736,939L1738,946L1743,957L1745,962L1746,967L1747,971L1751,982L1754,988L1773,1029L1785,1044L1818,1060L1806,1072L1801,1076L1797,1080L1794,1082L1790,1083L1785,1080L1778,1078L1770,1079L1755,1083L1745,1088L1726,1107L1719,1112L1679,1122L1699,1156L1702,1166L1708,1204L1726,1236L1740,1254L1739,1258L1739,1263L1738,1267L1740,1273L1745,1280L1778,1310L1786,1320L1791,1332L1796,1367L1815,1379L1815,1395L1809,1416L1788,1446L1773,1462L1762,1475L1762,1495L1733,1513L1709,1521L1676,1539L1666,1529L1654,1522L1638,1508L1634,1506L1628,1506L1612,1512L1572,1515L1557,1512L1500,1487L1477,1493L1479,1579L1450,1561L1432,1558L1389,1539L1343,1533L1317,1498L1303,1472L1297,1457L1294,1451L1286,1439L1275,1426L1251,1406L1237,1393L1221,1382L1212,1378L1179,1381L1155,1368L1090,1382L1090,1305L1093,1292L1092,1279L1090,1276L1087,1274L1078,1267L1069,1257L1129,1205L1120,1180L1122,1156L1127,1133L1185,1116L1203,1100L1207,1085L1209,1072L1209,1065L1207,1054L1209,1054L1255,1057L1256,1057L1311,1043L1337,1021L1343,1002L1343,1002L1382,969L1410,931L1435,923L1451,906L1454,899L1454,889L1450,883L1441,874L1432,863L1424,856L1416,852L1408,852L1394,854L1386,853L1378,849L1369,840L1368,827L1369,813L1372,804L1374,797L1379,791L1396,772L1407,762L1418,741L1416,703L1422,663L1426,658L1430,654L1435,653L1440,652L1446,651L1469,647L1481,642L1504,630L1513,620L1521,610L1525,601L1572,519L1580,498L1585,491L1590,487L1595,486L1632,483L1650,482L1668,498L1672,506L1674,511L1672,515L1672,518L1672,521L1674,529L1696,565L1711,579L1720,585L1727,584L1733,581L1739,575L1745,572L1753,572L1768,576L1775,576L1782,574L1794,574L1800,569L1803,562L1802,555L1801,547L1801,535L1800,529L1797,523L1795,517L1794,511L1795,502L1792,495L1794,484L1801,472L1836,451L1847,442L1858,423L1866,407L1868,381L1892,362L1943,362L1909,391L1891,421L1916,453L1918,462L1919,471L1915,482L1912,488L1909,493L1907,496L1905,499L1905,501L1906,504L1909,509L1912,515L1915,524L1919,532L1921,537L1924,539L1937,542L1941,544L1944,546L1947,551L1949,557L1951,566L1954,571L1957,575L1959,580L1961,588L1962,600L1956,636L1943,660L1936,670L1931,674Z</Path>
    </MapShape>
    <MapShape>
      <Id>1905</Id>
      <Name>Mongar</Name>
      <Path>M2964,1205L2969,1220L2958,1232L2984,1249L3000,1264L3030,1281L3035,1285L3038,1291L3038,1296L3045,1308L3048,1314L3048,1318L3049,1323L3051,1339L3007,1361L2963,1404L2955,1425L2952,1489L2949,1504L2947,1517L2938,1547L2926,1575L2911,1598L2890,1616L2814,1650L2791,1669L2772,1692L2741,1746L2732,1780L2712,1779L2700,1786L2694,1786L2685,1781L2676,1774L2668,1762L2657,1754L2649,1750L2639,1748L2630,1740L2624,1734L2613,1677L2600,1663L2595,1659L2553,1647L2516,1566L2514,1533L2522,1510L2529,1492L2531,1484L2532,1464L2531,1444L2520,1429L2519,1408L2518,1403L2515,1395L2499,1380L2495,1378L2484,1351L2473,1309L2464,1289L2451,1246L2467,1229L2471,1227L2493,1220L2550,1232L2612,1177L2636,1169L2655,1170L2677,1174L2684,1179L2710,1220L2800,1171L2814,1134L2816,1111L2814,1105L2806,1095L2800,1079L2808,1058L2820,1046L2846,1023L2848,1013L2847,993L2850,987L2856,984L2860,983L2872,980L2892,1016L2969,1120L2983,1154L2984,1159L2982,1170L2964,1205Z</Path>
    </MapShape>
    <MapShape>
      <Id>1906</Id>
      <Name>Pemagatsel</Name>
      <Path>M3073,1686L3031,1699L3028,1710L3009,1748L3007,1756L3006,1769L3009,1786L3010,1794L3006,1804L2990,1831L2975,1847L2963,1859L2955,1868L2945,1879L2934,1903L2919,1908L2888,1896L2898,1859L2902,1854L2903,1848L2903,1842L2890,1812L2864,1810L2854,1803L2846,1796L2839,1784L2832,1781L2822,1779L2778,1785L2747,1781L2732,1780L2741,1746L2772,1692L2791,1669L2814,1650L2890,1616L2911,1598L2926,1575L2938,1547L2947,1517L2949,1504L2996,1510L2981,1537L2969,1551L2968,1560L2968,1565L2976,1577L2986,1596L2991,1601L2995,1604L3018,1620L3023,1624L3038,1632L3078,1632L3080,1634L3073,1686Z</Path>
    </MapShape>
    <MapShape>
      <Id>1907</Id>
      <Name>Samdrup Jongkhar</Name>
      <Path>M3647,1488L3643,1492L3635,1510L3630,1532L3627,1555L3626,1578L3640,1619L3695,1674L3715,1714L3715,1714L3733,1786L3730,1806L3721,1848L3680,1889L3612,1899L3593,1890L3557,1859L3538,1851L3521,1856L3524,1872L3524,1891L3500,1902L3513,1919L3514,1940L3505,1954L3488,1952L3476,1934L3473,1914L3466,1896L3445,1885L3412,1891L3341,1937L3308,1953L3255,1960L3237,1959L3188,1944L3168,1945L3127,1959L3106,1961L3092,1948L3066,1892L3056,1876L3040,1871L2995,1868L2979,1871L2959,1885L2948,1904L2939,1927L2926,1950L2912,1964L2894,1976L2876,1984L2857,1989L2834,1990L2818,1984L2786,1964L2747,1955L2668,1956L2629,1952L2596,1952L2541,1977L2541,1977L2527,1941L2527,1935L2528,1931L2531,1922L2533,1915L2539,1906L2547,1899L2553,1896L2602,1885L2616,1876L2618,1876L2623,1877L2626,1878L2636,1855L2689,1853L2708,1845L2720,1826L2732,1780L2747,1781L2778,1785L2822,1779L2832,1781L2839,1784L2846,1796L2854,1803L2864,1810L2890,1812L2903,1842L2903,1848L2902,1854L2898,1859L2888,1896L2919,1908L2934,1903L2945,1879L2955,1868L2963,1859L2975,1847L2990,1831L3006,1804L3010,1794L3009,1786L3006,1769L3007,1756L3009,1748L3028,1710L3031,1699L3073,1686L3089,1695L3090,1695L3179,1644L3229,1655L3380,1602L3405,1557L3428,1536L3480,1519L3509,1515L3525,1516L3527,1513L3528,1509L3530,1469L3528,1446L3531,1426L3536,1412L3542,1407L3547,1406L3552,1410L3556,1415L3559,1420L3564,1441L3567,1448L3573,1460L3575,1466L3578,1471L3583,1476L3592,1481L3602,1484L3612,1486L3644,1487L3646,1488L3647,1488Z</Path>
    </MapShape>
    <MapShape>
      <Id>1908</Id>
      <Name>Tashigang</Name>
      <Path>M3647,1488L3646,1488L3644,1487L3612,1486L3602,1484L3592,1481L3583,1476L3578,1471L3575,1466L3573,1460L3567,1448L3564,1441L3559,1420L3556,1415L3552,1410L3547,1406L3542,1407L3536,1412L3531,1426L3528,1446L3530,1469L3528,1509L3527,1513L3525,1516L3509,1515L3480,1519L3428,1536L3405,1557L3380,1602L3229,1655L3179,1644L3090,1695L3089,1695L3073,1686L3080,1634L3078,1632L3038,1632L3023,1624L3018,1620L2995,1604L2991,1601L2986,1596L2976,1577L2968,1565L2968,1560L2969,1551L2981,1537L2996,1510L2949,1504L2952,1489L2955,1425L2963,1404L3007,1361L3051,1339L3049,1323L3048,1318L3048,1314L3045,1308L3038,1296L3038,1291L3035,1285L3030,1281L3000,1264L2984,1249L2958,1232L2969,1220L2964,1205L3007,1210L3110,1246L3114,1241L3141,1230L3146,1226L3172,1196L3184,1195L3249,1174L3288,1158L3318,1153L3327,1149L3333,1141L3336,1134L3336,1132L3355,1158L3356,1177L3362,1187L3395,1184L3481,1153L3511,1148L3552,1151L3566,1146L3599,1121L3612,1116L3637,1146L3735,1327L3739,1342L3731,1364L3696,1393L3681,1412L3677,1423L3673,1447L3670,1458L3664,1468L3650,1483L3647,1488Z</Path>
    </MapShape>
  </Shapes>
</LiveChartsMap>